ansible_please/__init__.py
ansible_please/ansible_dict.py
ansible_please/ansible_runner.py
ansible_please/ansible_task.py
ansible_please/base_ansible.py
ansible_please/inventory.py
ansible_please/playbook.py
ansible_please/utils.py
ansible_please/clusters/__init__.py
ansible_please/clusters/docker_cluster.py
ansible_please/examples/BasicDockerExample.ipynb
ansible_please/examples/test_input.yml
ansible_please/task_templates/__init__.py
ansible_please/task_templates/command.py
ansible_please/task_templates/docker_container.py
ansible_please/task_templates/pip.py
ansible_please-0.1.20.dist-info/AUTHORS.rst
ansible_please-0.1.20.dist-info/LICENSE
ansible_please-0.1.20.dist-info/METADATA
ansible_please-0.1.20.dist-info/WHEEL
ansible_please-0.1.20.dist-info/top_level.txt
ansible_please-0.1.20.dist-info/RECORD
