Metadata-Version: 2.1
Name: ansible-please
Version: 0.1.20
Summary: Helper package to make running Ansible a bit smoother
Home-page: https://github.com/shyamsn97/ansible_please
Author: Shyam Sudhakaran
Author-email: shyamsn97@gmail.com
License: MIT license
Keywords: ansible_please
Platform: UNKNOWN
Classifier: Intended Audience :: Developers
Classifier: License :: OSI Approved :: MIT License
Classifier: Natural Language :: English
Classifier: Programming Language :: Python :: 3.7
Classifier: Programming Language :: Python :: 3.8
Requires-Python: >=3.7
Requires-Dist: Click (>=7.0)
Requires-Dist: ansible-runner
Requires-Dist: attrs
Requires-Dist: loguru
Requires-Dist: omegaconf (==2.1.0.rc1)
Requires-Dist: cloudpickle
Requires-Dist: docker
